[
  {
    "text": "Many",
    "startMs": 380,
    "endMs": 720,
    "timestampMs": 550,
    "confidence": null
  },
  {
    "text": "days",
    "startMs": 800,
    "endMs": 1101,
    "timestampMs": 950,
    "confidence": null
  },
  {
    "text": "later,",
    "startMs": 1181,
    "endMs": 1621,
    "timestampMs": 1401,
    "confidence": null
  },
  {
    "text": "the",
    "startMs": 1821,
    "endMs": 1961,
    "timestampMs": 1891,
    "confidence": null
  },
  {
    "text": "lion",
    "startMs": 2061,
    "endMs": 2561,
    "timestampMs": 2311,
    "confidence": null
  },
  {
    "text": "was",
    "startMs": 2621,
    "endMs": 2801,
    "timestampMs": 2711,
    "confidence": null
  },
  {
    "text": "walking",
    "startMs": 2901,
    "endMs": 3422,
    "timestampMs": 3162,
    "confidence": null
  },
  {
    "text": "in",
    "startMs": 3482,
    "endMs": 3562,
    "timestampMs": 3522,
    "confidence": null
  },
  {
    "text": "the",
    "startMs": 3622,
    "endMs": 3722,
    "timestampMs": 3672,
    "confidence": null
  },
  {
    "text": "forest.",
    "startMs": 3802,
    "endMs": 4422,
    "timestampMs": 4112,
    "confidence": null
  },
  {
    "text": "Suddenly,",
    "startMs": 5643,
    "endMs": 6243,
    "timestampMs": 5943,
    "confidence": null
  },
  {
    "text": "he",
    "startMs": 6303,
    "endMs": 6423,
    "timestampMs": 6363,
    "confidence": null
  },
  {
    "text": "stepped",
    "startMs": 6523,
    "endMs": 6903,
    "timestampMs": 6713,
    "confidence": null
  },
  {
    "text": "into",
    "startMs": 6963,
    "endMs": 7243,
    "timestampMs": 7103,
    "confidence": null
  },
  {
    "text": "a",
    "startMs": 7323,
    "endMs": 7344,
    "timestampMs": 7334,
    "confidence": null
  },
  {
    "text": "net.",
    "startMs": 7464,
    "endMs": 7784,
    "timestampMs": 7624,
    "confidence": null
  },
  {
    "text": "It",
    "startMs": 8744,
    "endMs": 8844,
    "timestampMs": 8794,
    "confidence": null
  },
  {
    "text": "was",
    "startMs": 8924,
    "endMs": 9104,
    "timestampMs": 9014,
    "confidence": null
  },
  {
    "text": "a",
    "startMs": 9184,
    "endMs": 9224,
    "timestampMs": 9204,
    "confidence": null
  },
  {
    "text": "trap!",
    "startMs": 9344,
    "endMs": 9845,
    "timestampMs": 9594,
    "confidence": null
  },
  {
    "text": "The",
    "startMs": 10665,
    "endMs": 10805,
    "timestampMs": 10735,
    "confidence": null
  },
  {
    "text": "hunters",
    "startMs": 10885,
    "endMs": 11405,
    "timestampMs": 11145,
    "confidence": null
  },
  {
    "text": "made",
    "startMs": 11505,
    "endMs": 11826,
    "timestampMs": 11666,
    "confidence": null
  },
  {
    "text": "it.",
    "startMs": 11926,
    "endMs": 11986,
    "timestampMs": 11956,
    "confidence": null
  }
]